meterfuncs-0.2.0.dist-info/METADATA
meterfuncs-0.2.0.dist-info/WHEEL
meterfuncs-0.2.0.dist-info/entry_points.txt
meterfuncs/T.py
meterfuncs/__init__.py
meterfuncs/clean.py
meterfuncs/dataset.py
meterfuncs/evaluate.py
meterfuncs/nn.py
meterfuncs/train.py
meterfuncs/view.py
meterfuncs-0.2.0.dist-info/RECORD
