Metadata-Version: 2.1
Name: meterfuncs
Version: 0.2.0
Summary: meter reading model build functions
Author-Email: svtter <svtter@qq.com>
License: NOT OPEN
Requires-Python: <4.0,>=3.9
Requires-Dist: pydantic>=2.10.4
Requires-Dist: loguru>=0.7.3
